{
  "kind": "collectionType",
  "collectionName": "articles",
  "info": {
    "singularName": "article",
    "pluralName": "articles",
    "displayName": "Article",
    "description": ""
  },
  "options": {
    "draftAndPublish": true
  },
  "pluginOptions": {},
  "attributes": {
    "title": {
      "type": "string"
    },
    "slug": {
      "type": "uid",
      "targetField": "title"
    },
    "subtitle": {
      "type": "string"
    },
    "pass": {
      "type": "boolean"
    },
    "ai": {
      "type": "customField",
      "customField": "plugin::ai-text-generation.text-ai"
    }
  }
}
